<odoo>
    <data>
        <record id="view_partner_form_inh" model="ir.ui.view">
            <field name="name">res.partner.form.inh</field>
            <field name="model">res.partner</field>
            <field name="inherit_id" ref="base.view_partner_form"/>
            <field name="arch" type="xml">
                <xpath expr="sheet/notebook/page[@name='sales_purchases']" position="after">
                    <page string="Comisiones" name="commission" invisible="commission_active == False">
                        <group string="Asignacion">
                            <group>
                                <field name="commission_ids"/>
                                <field name="date"/>
                                <field name="commission_active" invisible="1"/>
                            </group>
                        </group>
                    </page>
                </xpath>
            </field>
        </record>
        <record id="view_res_partner_tree_inherit_rod_sales" model="ir.ui.view">
            <field name="name">res.partner.tree.inherit.rod_sales</field>
            <field name="model">res.partner</field>
            <field name="inherit_id" ref="base.view_partner_tree"/>
            <field name="arch" type="xml">
                <!-- Añadir nuevas columnas al final de la vista -->
                <xpath expr="//tree" position="inside">
                    <!-- Agregamos columnas adicionales -->
                    <field name="create_date"/>
                </xpath>
            </field>
        </record>
    </data>
</odoo>